{
  "title": "Artefact — Suite d'UI Moderne",
  "content": [
    {
      "type": "stack",
      "direction": "vertical",
      "align": "center",
      "gap": "4",
      "padding": "3rem 1.5rem",
      "children": [
        {
          "type": "badge",
          "text": "Composants HonoX Hono/JSX",
          "size": "lg",
          "colorPalette": "blue",
          "variant": "surface"
        },
        {
          "type": "heading",
          "as": "h1",
          "text": "Une suite de composants magnifiquement conçue et accessible.",
          "size": "5xl",
          "style": "text-align:center;max-width:48rem"
        },
        {
          "type": "text",
          "size": "lg",
          "content": "Un système de conception complet à 3 niveaux conçu pour HonoX, PandaCSS et Sveltia CMS. Rapide, léger et entièrement accessible, respectant les habitudes standard des utilisateurs.",
          "style": "text-align:center;max-width:42rem"
        },
        {
          "type": "stack",
          "direction": "horizontal",
          "gap": "4",
          "children": [
            {
              "type": "button",
              "text": "Voir la Vitrine",
              "variant": "solid",
              "colorPalette": "blue",
              "size": "lg",
              "onclick": "window.scrollTo({top: document.getElementById('carousel-showcase').offsetTop - 80, behavior: 'smooth'})"
            },
            {
              "type": "button",
              "text": "Hub de Composants",
              "variant": "outline",
              "size": "lg",
              "onclick": "window.scrollTo({top: document.getElementById('hub').offsetTop - 80, behavior: 'smooth'})"
            }
          ]
        }
      ]
    },
    {
      "type": "heading",
      "as": "h2",
      "text": "Vitrine des Onglets",
      "size": "3xl",
      "style": "text-align:center",
      "id": "tabs-showcase"
    },
    {
      "type": "text",
      "size": "md",
      "content": "Entièrement réimplémenté en Hono/JSX pur avec des indicateurs glissants, une activation du focus manuelle/automatique et une prise en charge complète de la navigation au clavier.",
      "style": "text-align:center;max-width:42rem;margin:0 auto"
    },
    {
      "type": "stack",
      "direction": "vertical",
      "padding": "1.5rem",
      "borderRadius": "1rem",
      "boxShadow": "sm",
      "children": [
        {
          "type": "tabs",
          "variant": "enclosed",
          "size": "md",
          "items": [
            {
              "value": "features",
              "label": "⚡ Fonctionnalités Clés",
              "content": [
                {
                  "type": "grid",
                  "columns": "{\"base\": 1, \"md\": 3}",
                  "gap": "6",
                  "children": [
                    {
                      "type": "card",
                      "title": "Ultra Rapide",
                      "description": "SSR par défaut avec une empreinte statique minimale. Ne s'hydrate que lorsque l'interaction est nécessaire.",
                      "children": [
                        {
                          "type": "badge",
                          "text": "Option Zéro JS",
                          "colorPalette": "green",
                          "variant": "subtle"
                        }
                      ]
                    },
                    {
                      "type": "card",
                      "title": "Entièrement Accessible",
                      "description": "Suivant exactement les normes WAI-ARIA. Entièrement navigable au clavier avec un tabIndex itinérant et des états aria.",
                      "children": [
                        {
                          "type": "badge",
                          "text": "Conforme A11y",
                          "colorPalette": "blue",
                          "variant": "subtle"
                        }
                      ]
                    },
                    {
                      "type": "card",
                      "title": "Design Époustouflant",
                      "description": "Transitions d'indicateur glissant et mises en page au pixel près adaptées aux habitudes modernes des utilisateurs.",
                      "children": [
                        {
                          "type": "badge",
                          "text": "Panda CSS",
                          "colorPalette": "purple",
                          "variant": "subtle"
                        }
                      ]
                    }
                  ]
                }
              ]
            },
            {
              "value": "pricing",
              "label": "💎 Plans Tarifaires",
              "content": [
                {
                  "type": "grid",
                  "columns": "{\"base\": 1, \"md\": 2}",
                  "gap": "6",
                  "children": [
                    {
                      "type": "card",
                      "title": "Débutant",
                      "description": "Parfait pour les projets personnels et les développeurs individuels souhaitant prototyper rapidement.",
                      "children": [
                        {
                          "type": "stack",
                          "direction": "horizontal",
                          "align": "baseline",
                          "gap": "1",
                          "children": [
                            {
                              "type": "heading",
                              "as": "p",
                              "text": "$0",
                              "size": "3xl"
                            },
                            {
                              "type": "text",
                              "size": "sm",
                              "content": "/mois"
                            }
                          ]
                        },
                        {
                          "type": "button",
                          "text": "Commencer",
                          "variant": "outline",
                          "colorPalette": "blue",
                          "size": "sm"
                        }
                      ]
                    },
                    {
                      "type": "card",
                      "title": "Pro",
                      "description": "Fonctionnalités complètes, pages illimitées, intégration analytique et support prioritaire dédié.",
                      "children": [
                        {
                          "type": "stack",
                          "direction": "horizontal",
                          "align": "baseline",
                          "gap": "1",
                          "children": [
                            {
                              "type": "heading",
                              "as": "p",
                              "text": "$29",
                              "size": "3xl"
                            },
                            {
                              "type": "text",
                              "size": "sm",
                              "content": "/mois"
                            }
                          ]
                        },
                        {
                          "type": "button",
                          "text": "Passer à Pro",
                          "variant": "solid",
                          "colorPalette": "blue",
                          "size": "sm"
                        }
                      ]
                    }
                  ]
                }
              ]
            },
            {
              "value": "tech-stack",
              "label": "🛠️ Stack Technologique",
              "content": [
                {
                  "type": "card",
                  "title": "Stack Web Moderne",
                  "description": "Conçu de A à Z pour une préparation maximale à la production et une vitesse optimale.",
                  "children": [
                    {
                      "type": "stack",
                      "direction": "vertical",
                      "gap": "4",
                      "children": [
                        {
                          "type": "stack",
                          "direction": "horizontal",
                          "justify": "between",
                          "align": "center",
                          "children": [
                            {
                              "type": "text",
                              "size": "sm",
                              "content": "Méta-Framework HonoX",
                              "style": "font-weight:bold"
                            },
                            {
                              "type": "badge",
                              "text": "Rapide et Server-First",
                              "colorPalette": "orange"
                            }
                          ]
                        },
                        {
                          "type": "stack",
                          "direction": "horizontal",
                          "justify": "between",
                          "align": "center",
                          "children": [
                            {
                              "type": "text",
                              "size": "sm",
                              "content": "Panda CSS",
                              "style": "font-weight:bold"
                            },
                            {
                              "type": "badge",
                              "text": "CSS-in-JS Sans Exécution",
                              "colorPalette": "amber"
                            }
                          ]
                        },
                        {
                          "type": "stack",
                          "direction": "horizontal",
                          "justify": "between",
                          "align": "center",
                          "children": [
                            {
                              "type": "text",
                              "size": "sm",
                              "content": "Outillage Bun",
                              "style": "font-weight:bold"
                            },
                            {
                              "type": "badge",
                              "text": "Vitesse Nouvelle Génération",
                              "colorPalette": "red"
                            }
                          ]
                        }
                      ]
                    }
                  ]
                }
              ]
            }
          ]
        }
      ]
    },
    {
      "type": "heading",
      "as": "h2",
      "text": "Implémentation Vedette du Carrousel",
      "size": "3xl",
      "style": "text-align:center",
      "id": "carousel-showcase"
    },
    {
      "type": "text",
      "size": "md",
      "content": "Démonstration de notre implémentation robuste en Hono/JSX du Slider Carousel d'Ark UI. Balayable, prêt pour la lecture automatique et entièrement accessible.",
      "style": "text-align:center;max-width:42rem;margin:0 auto"
    },
    {
      "type": "grid",
      "columns": "{\"base\": 1, \"md\": 2}",
      "gap": "8",
      "children": [
        {
          "type": "card",
          "title": "Carrousel Interactif à Lecture Automatique",
          "description": "Déclencheurs de lecture automatique, points personnalisés et pause au survol.",
          "children": [
            {
              "type": "carousel",
              "colorPalette": "blue",
              "loop": true,
              "pauseOnHover": true,
              "autoplayDelay": 3000,
              "slides": [
                {
                  "image": "https://images.unsplash.com/photo-1551288049-bebda4e38f71?w=800&q=80",
                  "caption": "Analytique en Temps Réel — Pulse fournit des données en direct et des tableaux de bord avec une latence de streaming inférieure à la seconde."
                },
                {
                  "image": "https://images.unsplash.com/photo-1518186285589-2f7649de83e0?w=800&q=80",
                  "caption": "Détection Alimentée par l'IA — La détection intelligente d'anomalies avertit votre équipe avant que la production ne tombe en panne."
                },
                {
                  "image": "https://images.unsplash.com/photo-1522071820081-009f0129c71c?w=800&q=80",
                  "caption": "Espaces de Travail d'Équipe Unifiés — Partagez des graphiques annotés et créez facilement des espaces de travail personnalisés."
                }
              ]
            }
          ]
        },
        {
          "type": "card",
          "title": "Carrousel en Boucle Multi-Diapositives",
          "description": "Affichage de 2 diapositives par page avec une grille riche et responsive.",
          "children": [
            {
              "type": "carousel",
              "colorPalette": "purple",
              "loop": true,
              "slidesPerPage": 2,
              "spacing": "12px",
              "slides": [
                {
                  "image": "https://images.unsplash.com/photo-1557683316-973673baf926?w=600&q=80",
                  "caption": "Diapositive 1"
                },
                {
                  "image": "https://images.unsplash.com/photo-1557682250-33bd709cbe85?w=600&q=80",
                  "caption": "Diapositive 2"
                },
                {
                  "image": "https://images.unsplash.com/photo-1557683311-eac922347aa1?w=600&q=80",
                  "caption": "Diapositive 3"
                },
                {
                  "image": "https://images.unsplash.com/photo-1557682224-5b8590cd9ec5?w=600&q=80",
                  "caption": "Diapositive 4"
                },
                {
                  "image": "https://images.unsplash.com/photo-1557683316-c31a9d3d0f27?w=600&q=80",
                  "caption": "Diapositive 5"
                },
                {
                  "image": "https://images.unsplash.com/photo-1557682257-2f9c37a3a5f3?w=600&q=80",
                  "caption": "Diapositive 6"
                }
              ]
            }
          ]
        }
      ]
    },
    {
      "type": "heading",
      "as": "h2",
      "text": "Hub Interactif de Composants",
      "size": "3xl",
      "style": "text-align:center",
      "id": "hub"
    },
    {
      "type": "text",
      "size": "md",
      "content": "Explorez les riches fonctionnalités du système de composants Artefact UI regroupées par catégorie d'utilisation.",
      "style": "text-align:center;max-width:42rem;margin:0 auto"
    },
    {
      "type": "heading",
      "as": "h3",
      "text": "Contrôles de Formulaire",
      "size": "xl",
      "style": "border-bottom:1px solid #e5e7eb;padding-bottom:0.5rem"
    },
    {
      "type": "grid",
      "columns": "{\"base\": 1, \"md\": 2, \"lg\": 3}",
      "gap": "6",
      "children": [
        {
          "type": "card",
          "title": "Contrôle Switch",
          "description": "Boutons bascule élégants",
          "children": [
            {
              "type": "stack",
              "direction": "vertical",
              "align": "start",
              "gap": "4",
              "children": [
                {
                  "type": "switch",
                  "label": "Bascule Petite",
                  "size": "sm"
                },
                {
                  "type": "switch",
                  "label": "Moyen Interactif",
                  "size": "md",
                  "checked": true
                },
                {
                  "type": "switch",
                  "label": "Grand Accent Bleu",
                  "size": "lg",
                  "colorPalette": "blue"
                }
              ]
            }
          ]
        },
        {
          "type": "card",
          "title": "Groupe de Cases à Cocher",
          "description": "Prise en charge des états normal et indéterminé",
          "children": [
            {
              "type": "stack",
              "direction": "vertical",
              "align": "start",
              "gap": "4",
              "children": [
                {
                  "type": "checkbox",
                  "label": "Case Petite",
                  "size": "sm"
                },
                {
                  "type": "checkbox",
                  "label": "État Indéterminé",
                  "size": "md",
                  "checked": "indeterminate"
                },
                {
                  "type": "checkbox",
                  "label": "Grand Interactif",
                  "size": "lg",
                  "colorPalette": "green",
                  "checked": true
                }
              ]
            }
          ]
        },
        {
          "type": "card",
          "title": "Curseur",
          "description": "Valeurs numériques ajustables",
          "children": [
            {
              "type": "stack",
              "direction": "vertical",
              "gap": "4",
              "children": [
                {
                  "type": "slider",
                  "label": "Curseur Unique",
                  "defaultValue": 45,
                  "showValueText": true
                },
                {
                  "type": "slider",
                  "label": "Sélection de Plage",
                  "defaultValue": [
                    15,
                    75
                  ],
                  "showValueText": true
                }
              ]
            }
          ]
        },
        {
          "type": "card",
          "title": "Groupe de Boutons Radio",
          "description": "Choix mutuellement exclusifs",
          "children": [
            {
              "type": "radioGroup",
              "defaultValue": "solid",
              "items": [
                {
                  "label": "Solide",
                  "value": "solid"
                },
                {
                  "label": "Liquide",
                  "value": "liquid"
                },
                {
                  "label": "Gaz",
                  "value": "gas"
                }
              ]
            }
          ]
        },
        {
          "type": "card",
          "title": "Groupe de Cartes Radio",
          "description": "Choix exclusifs façon carte",
          "children": [
            {
              "type": "stack",
              "direction": "vertical",
              "gap": "6",
              "children": [
                {
                  "type": "radioCardGroup",
                  "label": "Contour",
                  "defaultValue": "pro",
                  "items": [
                    {
                      "label": "Loisir",
                      "value": "hobby"
                    },
                    {
                      "label": "Pro",
                      "value": "pro"
                    },
                    {
                      "label": "Entreprise",
                      "value": "enterprise"
                    }
                  ]
                },
                {
                  "type": "radioCardGroup",
                  "label": "Subtil",
                  "variant": "subtle",
                  "defaultValue": "monthly",
                  "items": [
                    {
                      "label": "Mensuel",
                      "value": "monthly"
                    },
                    {
                      "label": "Annuel",
                      "value": "yearly"
                    }
                  ]
                },
                {
                  "type": "radioCardGroup",
                  "label": "Surface",
                  "variant": "surface",
                  "defaultValue": "standard",
                  "items": [
                    {
                      "label": "Standard",
                      "value": "standard"
                    },
                    {
                      "label": "Express",
                      "value": "express"
                    },
                    {
                      "label": "Nuit",
                      "value": "overnight",
                      "disabled": true
                    }
                  ]
                },
                {
                  "type": "radioCardGroup",
                  "label": "Plein",
                  "variant": "solid",
                  "defaultValue": "dark",
                  "items": [
                    {
                      "label": "Clair",
                      "value": "light"
                    },
                    {
                      "label": "Sombre",
                      "value": "dark"
                    },
                    {
                      "label": "Système",
                      "value": "system"
                    }
                  ]
                }
              ]
            }
          ]
        },
        {
          "type": "card",
          "title": "Groupe Segmenté",
          "description": "Contrôles de sélection glissants",
          "children": [
            {
              "type": "segmentGroup",
              "fitted": true,
              "defaultValue": "weekly",
              "items": [
                {
                  "label": "Hebdomadaire",
                  "value": "weekly"
                },
                {
                  "label": "Mensuel",
                  "value": "monthly"
                },
                {
                  "label": "Annuel",
                  "value": "yearly"
                }
              ]
            }
          ]
        },
        {
          "type": "card",
          "title": "Champ de Tags",
          "description": "Ajoutez et supprimez des tags de mots-clés",
          "children": [
            {
              "type": "tagsField",
              "label": "Centres d'intérêt",
              "helperText": "Appuyez sur Entrée pour ajouter un tag",
              "defaultValue": [
                "Hono",
                "Vite",
                "Panda"
              ]
            }
          ]
        },
        {
          "type": "card",
          "title": "Champ PIN",
          "description": "Saisie de code à usage unique avec collage et avancement automatique",
          "children": [
            {
              "type": "pinField",
              "label": "Code de vérification",
              "helperText": "Consultez votre e-mail pour le code à 6 chiffres",
              "count": 6,
              "otp": true,
              "blurOnComplete": true
            }
          ]
        },
        {
          "type": "card",
          "title": "Groupe de Notation",
          "description": "Notation par étoiles avec précision au demi-point",
          "children": [
            {
              "type": "stack",
              "direction": "vertical",
              "align": "start",
              "gap": "4",
              "children": [
                {
                  "type": "ratingGroup",
                  "label": "Évaluez votre expérience",
                  "defaultValue": 3
                },
                {
                  "type": "ratingGroup",
                  "label": "Précision au demi-étoile",
                  "allowHalf": true,
                  "defaultValue": 3.5,
                  "colorPalette": "blue"
                },
                {
                  "type": "ratingGroup",
                  "label": "Note moyenne",
                  "readOnly": true,
                  "allowHalf": true,
                  "defaultValue": 4.5,
                  "colorPalette": "orange",
                  "size": "sm"
                }
              ]
            }
          ]
        },
        {
          "type": "card",
          "title": "Champ",
          "description": "Champ étiqueté avec validation en direct",
          "children": [
            {
              "type": "field",
              "label": "Nom d'utilisateur",
              "defaultValue": "ab",
              "validator": "(value) => value.length >= 3 || \"Doit contenir au moins 3 caractères\""
            }
          ]
        },
        {
          "type": "card",
          "title": "Zone de Texte",
          "description": "Champ multiligne avec validation en direct",
          "children": [
            {
              "type": "textarea",
              "label": "Bio",
              "defaultValue": "Trop court",
              "validator": "(value) => value.length >= 20 || \"Dites-nous en un peu plus (20 caractères minimum)\""
            }
          ]
        }
      ]
    },
    {
      "type": "heading",
      "as": "h3",
      "text": "Sélecteurs Complexes",
      "size": "xl",
      "style": "border-bottom:1px solid #e5e7eb;padding-bottom:0.5rem"
    },
    {
      "type": "grid",
      "columns": "{\"base\": 1, \"md\": 2}",
      "gap": "6",
      "children": [
        {
          "type": "card",
          "title": "Sélecteur de Date",
          "description": "Sélecteurs avancés de date et de plage",
          "children": [
            {
              "type": "stack",
              "direction": "vertical",
              "gap": "4",
              "children": [
                {
                  "type": "datePicker",
                  "label": "Choisissez une seule date",
                  "selectionMode": "single"
                },
                {
                  "type": "datePicker",
                  "label": "Choisissez une plage de dates",
                  "selectionMode": "range",
                  "colorPalette": "purple"
                }
              ]
            }
          ]
        },
        {
          "type": "card",
          "title": "Sélection Déroulante",
          "description": "Listes déroulantes accessibles et zones de saisie avec autocomplétion",
          "children": [
            {
              "type": "stack",
              "direction": "vertical",
              "gap": "4",
              "children": [
                {
                  "type": "select",
                  "label": "Sélection de Framework",
                  "placeholder": "Sélectionnez un framework",
                  "items": [
                    {
                      "label": "React",
                      "value": "react"
                    },
                    {
                      "label": "Solid",
                      "value": "solid"
                    },
                    {
                      "label": "Svelte",
                      "value": "svelte"
                    },
                    {
                      "label": "Vue",
                      "value": "vue"
                    },
                    {
                      "label": "Hono",
                      "value": "hono"
                    }
                  ]
                },
                {
                  "type": "combobox",
                  "label": "Combobox Consultable",
                  "placeholder": "Tapez pour rechercher...",
                  "items": [
                    {
                      "label": "React",
                      "value": "react"
                    },
                    {
                      "label": "Solid",
                      "value": "solid"
                    },
                    {
                      "label": "Svelte",
                      "value": "svelte"
                    },
                    {
                      "label": "Vue",
                      "value": "vue"
                    },
                    {
                      "label": "Hono",
                      "value": "hono"
                    }
                  ]
                }
              ]
            }
          ]
        },
        {
          "type": "card",
          "title": "Sélecteur de Couleur",
          "description": "Sélecteur de spectre de couleurs complet",
          "children": [
            {
              "type": "colorPicker",
              "trigger": true,
              "defaultValue": "#3b82f6",
              "label": "Choisissez la Couleur du Thème"
            }
          ]
        },
        {
          "type": "card",
          "title": "Téléversement de Fichiers",
          "description": "Zone de glisser-déposer avec règles de validation",
          "children": [
            {
              "type": "fileUpload",
              "label": "Téléverser des Images",
              "name": "images",
              "accept": "image/*",
              "maxFiles": 2,
              "dropzoneText": "Glissez-déposez ou parcourez les fichiers"
            }
          ]
        }
      ]
    },
    {
      "type": "heading",
      "as": "h3",
      "text": "Superpositions et Navigation",
      "size": "xl",
      "style": "border-bottom:1px solid #e5e7eb;padding-bottom:0.5rem"
    },
    {
      "type": "grid",
      "columns": "{\"base\": 1, \"md\": 2, \"lg\": 3}",
      "gap": "6",
      "children": [
        {
          "type": "card",
          "title": "Popover et Infobulle",
          "description": "Boîtes d'information contextuelles",
          "children": [
            {
              "type": "stack",
              "direction": "horizontal",
              "align": "start",
              "gap": "4",
              "children": [
                {
                  "type": "popover",
                  "triggerText": "Déclencher le Popover",
                  "title": "Info Rapide",
                  "body": "Les popovers sont parfaits pour afficher un contexte détaillé au clic.",
                  "showArrow": true
                },
                {
                  "type": "tooltip",
                  "triggerText": "Infobulle au Survol",
                  "content": "Agréable et accessible !",
                  "showArrow": true
                }
              ]
            }
          ]
        },
        {
          "type": "card",
          "title": "Modales et Tiroirs",
          "description": "Panneaux superposés avec piégeage du focus",
          "children": [
            {
              "type": "stack",
              "direction": "horizontal",
              "align": "start",
              "gap": "4",
              "children": [
                {
                  "type": "dialog",
                  "trigger": [
                    {
                      "type": "button",
                      "variant": "solid",
                      "colorPalette": "blue",
                      "text": "Ouvrir la Modale"
                    }
                  ],
                  "title": "Supprimer l'Espace de Travail",
                  "description": "Êtes-vous absolument certain de vouloir supprimer cet espace de travail ?",
                  "body": "Cette action est irréversible et toutes vos données seront définitivement effacées.",
                  "confirmText": "Supprimer",
                  "cancelText": "Annuler",
                  "footer": [
                    {
                      "type": "button",
                      "variant": "outline",
                      "text": "Notifier l'Équipe",
                      "onclick": "window.dispatchEvent(new CustomEvent('park-ui:toast:create', { detail: { id: Math.random().toString(36).substring(2, 9), title: 'Équipe Notifiée', description: 'Votre équipe a été alertée de cette suppression.', closable: true, type: 'info' } }))"
                    }
                  ]
                },
                {
                  "type": "drawer",
                  "trigger": [
                    {
                      "type": "button",
                      "variant": "outline",
                      "text": "Ouvrir le Tiroir des Paramètres"
                    }
                  ],
                  "title": "Paramètres du Projet",
                  "description": "Configurez les propriétés de l'espace de travail",
                  "confirmText": "Enregistrer les Modifications",
                  "cancelText": "Ignorer",
                  "footer": [
                    {
                      "type": "button",
                      "variant": "outline",
                      "colorPalette": "blue",
                      "text": "Recharger le Tableau",
                      "onclick": "window.dispatchEvent(new CustomEvent('paginated-table:reload'))"
                    }
                  ],
                  "children": [
                    {
                      "type": "text",
                      "size": "sm",
                      "content": "Gérez directement ici vos connexions à la base de données, les niveaux d'accès des membres et vos préférences de facturation."
                    },
                    {
                      "type": "paginatedTable",
                      "url": "/api/posts/index.json",
                      "dataKey": "posts",
                      "pageSize": 3,
                      "columns": [
                        {
                          "header": "Titre",
                          "key": "title"
                        },
                        {
                          "header": "Auteur",
                          "key": "author"
                        },
                        {
                          "header": "Date",
                          "key": "date"
                        }
                      ]
                    }
                  ]
                }
              ]
            }
          ]
        },
        {
          "type": "card",
          "title": "Menus Déroulants d'Action",
          "description": "Déclencheurs de listes d'actions imbricables",
          "children": [
            {
              "type": "dropdown",
              "triggerText": "Actions de l'Espace de Travail",
              "items": [
                {
                  "type": "item",
                  "label": "Voir le Profil",
                  "value": "profile"
                },
                {
                  "type": "item",
                  "label": "Facturation",
                  "value": "billing"
                },
                {
                  "type": "separator"
                },
                {
                  "type": "submenu",
                  "label": "Inviter des Membres",
                  "items": [
                    {
                      "type": "item",
                      "label": "par E-mail",
                      "value": "email"
                    },
                    {
                      "type": "item",
                      "label": "par Lien Secret",
                      "value": "link"
                    }
                  ]
                }
              ]
            }
          ]
        },
        {
          "type": "card",
          "title": "Carte au Survol",
          "description": "Fenêtre d'information contextuelle au survol",
          "children": [
            {
              "type": "hoverCard",
              "triggerText": "Survolez pour voir les détails de l'auteur",
              "showArrow": true,
              "title": "À propos de Jules",
              "description": "Designer UI senior et architecte front-end spécialisé dans les suites HonoX."
            }
          ]
        },
        {
          "type": "card",
          "title": "Contenu Rétractable",
          "description": "Sections accordéon fluides",
          "children": [
            {
              "type": "collapsible",
              "trigger": [
                {
                  "type": "button",
                  "variant": "outline",
                  "size": "sm",
                  "text": "Basculer les Détails"
                }
              ],
              "children": [
                {
                  "type": "text",
                  "size": "sm",
                  "content": "Notre piégeage du focus accessible et notre navigation au clavier fonctionnent parfaitement sur tous les appareils."
                }
              ]
            }
          ]
        },
        {
          "type": "card",
          "title": "Fil d'Ariane",
          "description": "Hiérarchies de navigation",
          "children": [
            {
              "type": "breadcrumb",
              "items": [
                {
                  "label": "Accueil",
                  "href": "/"
                },
                {
                  "label": "Bibliothèque",
                  "href": "/library"
                },
                {
                  "label": "Vitrine"
                }
              ]
            }
          ]
        }
      ]
    },
    {
      "type": "heading",
      "as": "h3",
      "text": "Retour et Utilitaires",
      "size": "xl",
      "style": "border-bottom:1px solid #e5e7eb;padding-bottom:0.5rem"
    },
    {
      "type": "grid",
      "columns": "{\"base\": 1, \"md\": 2, \"lg\": 3}",
      "gap": "6",
      "children": [
        {
          "type": "card",
          "title": "Barres de Progression",
          "description": "Indicateurs de progression linéaires et circulaires",
          "children": [
            {
              "type": "stack",
              "direction": "vertical",
              "gap": "4",
              "children": [
                {
                  "type": "progress",
                  "label": "Téléversement des Données",
                  "value": 72,
                  "showValueText": true
                },
                {
                  "type": "progress",
                  "label": "Traitement en Cours",
                  "progressType": "circular"
                }
              ]
            }
          ]
        },
        {
          "type": "card",
          "title": "Squelettes et Alertes",
          "description": "Widgets de retour et d'espace réservé",
          "children": [
            {
              "type": "stack",
              "direction": "vertical",
              "gap": "4",
              "children": [
                {
                  "type": "skeleton",
                  "shape": "text",
                  "noOfLines": 2
                },
                {
                  "type": "alert",
                  "status": "success",
                  "variant": "surface",
                  "title": "Synchronisation réussie",
                  "description": "Toutes les modifications sont entièrement conservées dans le stockage local."
                }
              ]
            }
          ]
        },
        {
          "type": "card",
          "title": "Presse-papiers et Toast",
          "description": "Utilitaires interactifs de retour utilisateur",
          "children": [
            {
              "type": "stack",
              "direction": "vertical",
              "gap": "4",
              "children": [
                {
                  "type": "clipboard",
                  "label": "Commande de Clonage",
                  "value": "git clone https://github.com/honojs/honox"
                },
                {
                  "type": "toast"
                },
                {
                  "type": "button",
                  "variant": "outline",
                  "size": "sm",
                  "text": "Envoyer un Toast",
                  "onclick": "window.dispatchEvent(new CustomEvent('park-ui:toast:create', { detail: { id: Math.random().toString(36).substring(2, 9), title: 'Tâche Envoyée', description: 'Action du composant interactif enregistrée.', closable: true, type: 'success' } }))"
                }
              ]
            }
          ]
        },
        {
          "type": "card",
          "title": "Éditable",
          "description": "Cliquez pour éditer en ligne, sur place",
          "children": [
            {
              "type": "stack",
              "direction": "vertical",
              "gap": "4",
              "children": [
                {
                  "type": "editable",
                  "label": "Nom du projet",
                  "defaultValue": "Artefact UI Suite"
                },
                {
                  "type": "editable",
                  "label": "Description",
                  "placeholder": "Ajoutez une description…"
                }
              ]
            }
          ]
        }
      ]
    }
  ]
}
